README.rst
setup.py
ocapi/__init__.py
ocapi/ajax.py
ocapi/api.py
ocapi/brythonapi.py
ocapi/info.py
ocapi/prod_func.py
ocapi/product.py
ocapi/urllibtls.py
ocapi/version.py
ocapi.egg-info/PKG-INFO
ocapi.egg-info/SOURCES.txt
ocapi.egg-info/dependency_links.txt
ocapi.egg-info/top_level.txt