Metadata-Version: 1.1
Name: ocapi
Version: 0.9.37
Summary: API connector to Pripravto service
Home-page: http://www.pripravto.cz
Author: Zdenek Dlauhy, Michal Dlauhy
Author-email: info@pripravto.cz
License: UNKNOWN
Keywords: ocapi,automatization,api,furniture,optimcabinet,vizualization,images,calculation,optimalization
Platform: UNKNOWN
Classifier: Development Status :: 4 - Beta
Classifier: Intended Audience :: Developers
Classifier: Programming Language :: Python
Classifier: Topic :: Software Development :: Libraries :: Python Modules
